setup.py
amigo/__init__.py
amigo/addtext.py
amigo/geom.py
amigo.egg-info/PKG-INFO
amigo.egg-info/SOURCES.txt
amigo.egg-info/dependency_links.txt
amigo.egg-info/not-zip-safe
amigo.egg-info/top_level.txt