Metadata-Version: 1.0
Name: amigo
Version: 0.0.1
Summary: common utility tools suporting Nova and Etna codes
Home-page: https://github.com/twistersi/Amigo
Author: Simon McIntosh
Author-email: simon.mcintosh@ukaea.uk
License: MIT
Platform: UNKNOWN
